voluptuous_apispec/__init__.py
voluptuous_apispec-0.0.1.dist-info/DESCRIPTION.rst
voluptuous_apispec-0.0.1.dist-info/METADATA
voluptuous_apispec-0.0.1.dist-info/RECORD
voluptuous_apispec-0.0.1.dist-info/WHEEL
voluptuous_apispec-0.0.1.dist-info/metadata.json
voluptuous_apispec-0.0.1.dist-info/top_level.txt
